extractpdf/__init__.py
extractpdf/base_parser.py
extractpdf/downloader.py
extractpdf/exceptions.py
extractpdf/image.py
extractpdf/main.py
extractpdf/parser.py
extractpdf/pdf_extractor.py
extractpdf/shell_parser.py
extractpdf/utils.py
extractpdf/tests/__init__.py
extractpdf/tests/downloader_test.py
extractpdf/tests/main_test.py
extractpdf/tests/pdf_extractor_test.py
pdf_extract/__init__.py
pdf_extract/downloader.py
pdf_extract/exceptions.py
pdf_extract/image.py
pdf_extract/main.py
pdf_extract/parser.py
pdf_extract/utils.py
pdf_extract/tests/__init__.py
pdf_extract/tests/downloader_test.py
pdf_extract/tests/main_test.py
extractpdf-0.0.4.dist-info/LICENSE
extractpdf-0.0.4.dist-info/METADATA
extractpdf-0.0.4.dist-info/WHEEL
extractpdf-0.0.4.dist-info/top_level.txt
extractpdf-0.0.4.dist-info/RECORD
