Metadata-Version: 2.1
Name: extractpdf
Version: 0.0.4
Summary: A tool to extract text from PDF files.
Home-page: https://github.com/WeAreDevelopers-com/extractpdf
Author: WeAreDevelopers
Author-email: liad@wearedevelopers.com
License: UNKNOWN
Platform: UNKNOWN
Classifier: Programming Language :: Python :: 3
Classifier: License :: OSI Approved :: MIT License
Classifier: Operating System :: OS Independent
